<annotation>
	<folder>images</folder>
	<filename>268.jpg</filename>
	<path>/home/marcocelia/.venv/cvtf/lib/python3.8/site-packages/tensorflow/models/images/268.jpg</path>
	<source>
		<database>Unknown</database>
	</source>
	<size>
		<width>275</width>
		<height>183</height>
		<depth>3</depth>
	</size>
	<segmented>0</segmented>
	<object>
		<name>mask</name>
		<pose>Unspecified</pose>
		<truncated>0</truncated>
		<difficult>0</difficult>
		<bndbox>
			<xmin>115</xmin>
			<ymin>69</ymin>
			<xmax>154</xmax>
			<ymax>103</ymax>
		</bndbox>
	</object>
	<object>
		<name>mask</name>
		<pose>Unspecified</pose>
		<truncated>0</truncated>
		<difficult>0</difficult>
		<bndbox>
			<xmin>164</xmin>
			<ymin>79</ymin>
			<xmax>192</xmax>
			<ymax>102</ymax>
		</bndbox>
	</object>
	<object>
		<name>mask</name>
		<pose>Unspecified</pose>
		<truncated>0</truncated>
		<difficult>0</difficult>
		<bndbox>
			<xmin>225</xmin>
			<ymin>89</ymin>
			<xmax>252</xmax>
			<ymax>111</ymax>
		</bndbox>
	</object>
</annotation>